__init__.py
say_hello_yapbarry.py
Sayhelloyapbarry3-0.0.1.dist-info/METADATA
Sayhelloyapbarry3-0.0.1.dist-info/WHEEL
Sayhelloyapbarry3-0.0.1.dist-info/top_level.txt
Sayhelloyapbarry3-0.0.1.dist-info/RECORD
