Metadata-Version: 2.1
Name: Sayhelloyapbarry3
Version: 0.0.1
Summary: just saying hello
Author: Barry Yap
Author-email: yapweiminbarry@gmail.com
